{
  "timestamp": "2026-06-10 20:39",
  "fecha": "10/06/2026",
  "hora": "20:39",
  "panel": {
    "data": [
      {
        "sym": "CRES",
        "price": 1761.0,
        "chgPct": 1.85,
        "vol": 372971,
        "volRatio": 1.59,
        "rsi": 63.3,
        "rsiPrev": 63.2,
        "macd": "bullish",
        "trend": "uptrend",
        "bb": "middle",
        "score": 100,
        "rec": "STRONG_BUY",
        "sl": 1653.11,
        "sl_pct": 6.13,
        "tp1": 1940.82,
        "tp2": 2084.68,
        "sup": 1541.0,
        "res": 1850.0,
        "atr": 71.93,
        "bid": 1757.48,
        "ask": 1764.52
      },
      {
        "sym": "ALUA",
        "price": 1016.0,
        "chgPct": 0.79,
        "vol": 693513,
        "volRatio": 1.35,
        "rsi": 69.5,
        "rsiPrev": 70.1,
        "macd": "bullish",
        "trend": "uptrend",
        "bb": "middle",
        "score": 95,
        "rec": "STRONG_BUY",
        "sl": 962.91,
        "sl_pct": 5.23,
        "tp1": 1104.48,
        "tp2": 1175.27,
        "sup": 894.5,
        "res": 1035.0,
        "atr": 35.39,
        "bid": 1013.97,
        "ask": 1018.03
      },
      {
        "sym": "CADO",
        "price": 573.0,
        "chgPct": -0.35,
        "vol": 16242,
        "volRatio": 1.48,
        "rsi": 54.8,
        "rsiPrev": 63.0,
        "macd": "bullish",
        "trend": "uptrend",
        "bb": "middle",
        "score": 95,
        "rec": "STRONG_BUY",
        "sl": 557.25,
        "sl_pct": 2.75,
        "tp1": 599.25,
        "tp2": 620.25,
        "sup": 548.0,
        "res": 578.0,
        "atr": 10.5,
        "bid": 571.85,
        "ask": 574.15
      },
      {
        "sym": "IRSA",
        "price": 2290.0,
        "chgPct": -1.93,
        "vol": 92400,
        "volRatio": 1.01,
        "rsi": 63.4,
        "rsiPrev": 70.5,
        "macd": "bullish",
        "trend": "uptrend",
        "bb": "middle",
        "score": 95,
        "rec": "STRONG_BUY",
        "sl": 2121.25,
        "sl_pct": 7.37,
        "tp1": 2571.25,
        "tp2": 2796.25,
        "sup": 1955.0,
        "res": 2420.0,
        "atr": 112.5,
        "bid": 2285.42,
        "ask": 2294.58
      },
      {
        "sym": "BMA",
        "price": 13160.0,
        "chgPct": -1.42,
        "vol": 399128,
        "volRatio": 1.24,
        "rsi": 67.8,
        "rsiPrev": 75.7,
        "macd": "bullish",
        "trend": "uptrend",
        "bb": "middle",
        "score": 95,
        "rec": "STRONG_BUY",
        "sl": 12158.98,
        "sl_pct": 7.61,
        "tp1": 14828.37,
        "tp2": 16163.06,
        "sup": 10102.92,
        "res": 13762.24,
        "atr": 667.35,
        "bid": 13133.68,
        "ask": 13186.32
      },
      {
        "sym": "TXAR",
        "price": 684.0,
        "chgPct": 0.29,
        "vol": 1209524,
        "volRatio": 1.19,
        "rsi": 66.1,
        "rsiPrev": 69.7,
        "macd": "bullish",
        "trend": "uptrend",
        "bb": "middle",
        "score": 95,
        "rec": "STRONG_BUY",
        "sl": 637.82,
        "sl_pct": 6.75,
        "tp1": 760.96,
        "tp2": 822.54,
        "sup": 593.0,
        "res": 710.0,
        "atr": 30.79,
        "bid": 682.63,
        "ask": 685.37
      },
      {
        "sym": "EDN",
        "price": 1969.0,
        "chgPct": -0.51,
        "vol": 479751,
        "volRatio": 0.65,
        "rsi": 63.0,
        "rsiPrev": 66.7,
        "macd": "bullish",
        "trend": "uptrend",
        "bb": "middle",
        "score": 85,
        "rec": "STRONG_BUY",
        "sl": 1828.11,
        "sl_pct": 7.16,
        "tp1": 2203.82,
        "tp2": 2391.68,
        "sup": 1655.0,
        "res": 2150.0,
        "atr": 93.93,
        "bid": 1965.06,
        "ask": 1972.94
      },
      {
        "sym": "BBAR",
        "price": 8935.0,
        "chgPct": -1.87,
        "vol": 240425,
        "volRatio": 0.92,
        "rsi": 64.1,
        "rsiPrev": 72.6,
        "macd": "bullish",
        "trend": "uptrend",
        "bb": "middle",
        "score": 85,
        "rec": "STRONG_BUY",
        "sl": 8225.46,
        "sl_pct": 7.94,
        "tp1": 10117.57,
        "tp2": 11063.62,
        "sup": 6885.38,
        "res": 9548.92,
        "atr": 473.03,
        "bid": 8917.13,
        "ask": 8952.87
      },
      {
        "sym": "PAMP",
        "price": 5035.0,
        "chgPct": 0.1,
        "vol": 653177,
        "volRatio": 0.61,
        "rsi": 60.4,
        "rsiPrev": 63.5,
        "macd": "bullish",
        "trend": "uptrend",
        "bb": "middle",
        "score": 85,
        "rec": "STRONG_BUY",
        "sl": 4785.89,
        "sl_pct": 4.95,
        "tp1": 5450.18,
        "tp2": 5782.32,
        "sup": 4632.5,
        "res": 5310.0,
        "atr": 166.07,
        "bid": 5024.93,
        "ask": 5045.07
      },
      {
        "sym": "CEPU",
        "price": 2285.0,
        "chgPct": 1.47,
        "vol": 728258,
        "volRatio": 0.89,
        "rsi": 60.2,
        "rsiPrev": 62.1,
        "macd": "bullish",
        "trend": "uptrend",
        "bb": "middle",
        "score": 85,
        "rec": "STRONG_BUY",
        "sl": 2147.54,
        "sl_pct": 6.02,
        "tp1": 2514.11,
        "tp2": 2697.39,
        "sup": 2020.0,
        "res": 2449.0,
        "atr": 91.64,
        "bid": 2280.43,
        "ask": 2289.57
      },
      {
        "sym": "MOLI",
        "price": 2715.0,
        "chgPct": 0.93,
        "vol": 8346,
        "volRatio": 0.85,
        "rsi": 67.4,
        "rsiPrev": 67.8,
        "macd": "bullish",
        "trend": "uptrend",
        "bb": "middle",
        "score": 85,
        "rec": "STRONG_BUY",
        "sl": 2521.61,
        "sl_pct": 7.12,
        "tp1": 3037.32,
        "tp2": 3295.18,
        "sup": 2475.0,
        "res": 2910.0,
        "atr": 128.93,
        "bid": 2709.57,
        "ask": 2720.43
      },
      {
        "sym": "HARG",
        "price": 1745.0,
        "chgPct": -1.97,
        "vol": 13478,
        "volRatio": 0.45,
        "rsi": 68.9,
        "rsiPrev": 77.9,
        "macd": "bullish",
        "trend": "uptrend",
        "bb": "middle",
        "score": 85,
        "rec": "STRONG_BUY",
        "sl": 1626.61,
        "sl_pct": 6.78,
        "tp1": 1942.32,
        "tp2": 2100.18,
        "sup": 1475.0,
        "res": 1875.0,
        "atr": 78.93,
        "bid": 1741.51,
        "ask": 1748.49
      },
      {
        "sym": "AUSO",
        "price": 3725.0,
        "chgPct": 0.95,
        "vol": 7811,
        "volRatio": 0.52,
        "rsi": 68.2,
        "rsiPrev": 69.0,
        "macd": "bullish",
        "trend": "uptrend",
        "bb": "middle",
        "score": 85,
        "rec": "STRONG_BUY",
        "sl": 3424.46,
        "sl_pct": 8.07,
        "tp1": 4225.89,
        "tp2": 4626.61,
        "sup": 3300.0,
        "res": 3890.0,
        "atr": 200.36,
        "bid": 3717.55,
        "ask": 3732.45
      },
      {
        "sym": "BBAR",
        "price": 8935.0,
        "chgPct": -1.87,
        "vol": 240425,
        "volRatio": 0.92,
        "rsi": 64.1,
        "rsiPrev": 72.6,
        "macd": "bullish",
        "trend": "uptrend",
        "bb": "middle",
        "score": 85,
        "rec": "STRONG_BUY",
        "sl": 8225.46,
        "sl_pct": 7.94,
        "tp1": 10117.57,
        "tp2": 11063.62,
        "sup": 6885.38,
        "res": 9548.92,
        "atr": 473.03,
        "bid": 8917.13,
        "ask": 8952.87
      },
      {
        "sym": "TGNO4",
        "price": 4157.5,
        "chgPct": 3.16,
        "vol": 206164,
        "volRatio": 1.67,
        "rsi": 55.7,
        "rsiPrev": 52.0,
        "macd": "bullish",
        "trend": "downtrend",
        "bb": "middle",
        "score": 80,
        "rec": "STRONG_BUY",
        "sl": 3915.09,
        "sl_pct": 5.83,
        "tp1": 4561.52,
        "tp2": 4884.73,
        "sup": 3600.0,
        "res": 4350.0,
        "atr": 161.61,
        "bid": 4149.19,
        "ask": 4165.81
      },
      {
        "sym": "CTIO",
        "price": 1830.0,
        "chgPct": 1.95,
        "vol": 125163,
        "volRatio": 2.67,
        "rsi": 56.5,
        "rsiPrev": 56.5,
        "macd": "bullish",
        "trend": "downtrend",
        "bb": "middle",
        "score": 80,
        "rec": "STRONG_BUY",
        "sl": 1712.68,
        "sl_pct": 6.41,
        "tp1": 2025.54,
        "tp2": 2181.96,
        "sup": 1685.0,
        "res": 1890.0,
        "atr": 78.21,
        "bid": 1826.34,
        "ask": 1833.66
      },
      {
        "sym": "TGSU2",
        "price": 9290.0,
        "chgPct": 2.82,
        "vol": 420737,
        "volRatio": 1.45,
        "rsi": 61.6,
        "rsiPrev": 63.1,
        "macd": "bullish",
        "trend": "downtrend",
        "bb": "middle",
        "score": 75,
        "rec": "STRONG_BUY",
        "sl": 8804.64,
        "sl_pct": 5.22,
        "tp1": 10098.93,
        "tp2": 10746.07,
        "sup": 8420.0,
        "res": 9560.0,
        "atr": 323.57,
        "bid": 9271.42,
        "ask": 9308.58
      },
      {
        "sym": "GGAL",
        "price": 7485.0,
        "chgPct": -0.8,
        "vol": 3777224,
        "volRatio": 1.04,
        "rsi": 74.2,
        "rsiPrev": 79.1,
        "macd": "bullish",
        "trend": "uptrend",
        "bb": "middle",
        "score": 70,
        "rec": "BUY",
        "sl": 7084.29,
        "sl_pct": 5.35,
        "tp1": 8152.86,
        "tp2": 8687.14,
        "sup": 5950.0,
        "res": 7725.0,
        "atr": 267.14,
        "bid": 7470.03,
        "ask": 7499.97
      },
      {
        "sym": "LEDE",
        "price": 756.0,
        "chgPct": 3.28,
        "vol": 16576,
        "volRatio": 0.83,
        "rsi": 62.9,
        "rsiPrev": 52.8,
        "macd": "bullish",
        "trend": "downtrend",
        "bb": "middle",
        "score": 65,
        "rec": "BUY",
        "sl": 704.25,
        "sl_pct": 6.85,
        "tp1": 842.25,
        "tp2": 911.25,
        "sup": 708.0,
        "res": 799.0,
        "atr": 34.5,
        "bid": 754.49,
        "ask": 757.51
      },
      {
        "sym": "BYMA",
        "price": 286.25,
        "chgPct": 0.44,
        "vol": 2488126,
        "volRatio": 0.67,
        "rsi": 60.4,
        "rsiPrev": 57.4,
        "macd": "bullish",
        "trend": "downtrend",
        "bb": "middle",
        "score": 60,
        "rec": "BUY",
        "sl": 270.37,
        "sl_pct": 5.55,
        "tp1": 312.72,
        "tp2": 333.9,
        "sup": 269.0,
        "res": 315.0,
        "atr": 10.59,
        "bid": 285.68,
        "ask": 286.82
      },
      {
        "sym": "MIRG",
        "price": 16725.0,
        "chgPct": 0.0,
        "vol": 2077,
        "volRatio": 0.61,
        "rsi": 57.4,
        "rsiPrev": 58.1,
        "macd": "bullish",
        "trend": "downtrend",
        "bb": "middle",
        "score": 60,
        "rec": "BUY",
        "sl": 15814.29,
        "sl_pct": 5.45,
        "tp1": 18242.86,
        "tp2": 19457.14,
        "sup": 16000.0,
        "res": 17950.0,
        "atr": 607.14,
        "bid": 16691.55,
        "ask": 16758.45
      },
      {
        "sym": "SUPV",
        "price": 2922.5,
        "chgPct": -1.43,
        "vol": 400623,
        "volRatio": 0.54,
        "rsi": 72.3,
        "rsiPrev": 78.2,
        "macd": "bullish",
        "trend": "uptrend",
        "bb": "middle",
        "score": 60,
        "rec": "BUY",
        "sl": 2696.43,
        "sl_pct": 7.74,
        "tp1": 3299.29,
        "tp2": 3600.71,
        "sup": 2201.0,
        "res": 3030.0,
        "atr": 150.71,
        "bid": 2916.66,
        "ask": 2928.34
      },
      {
        "sym": "TECO2",
        "price": 4280.0,
        "chgPct": -0.12,
        "vol": 95673,
        "volRatio": 0.48,
        "rsi": 72.9,
        "rsiPrev": 73.8,
        "macd": "bullish",
        "trend": "uptrend",
        "bb": "middle",
        "score": 60,
        "rec": "BUY",
        "sl": 3970.89,
        "sl_pct": 7.22,
        "tp1": 4795.18,
        "tp2": 5207.32,
        "sup": 3442.5,
        "res": 4465.0,
        "atr": 206.07,
        "bid": 4271.44,
        "ask": 4288.56
      },
      {
        "sym": "METR",
        "price": 1917.0,
        "chgPct": -0.52,
        "vol": 190825,
        "volRatio": 0.65,
        "rsi": 52.3,
        "rsiPrev": 53.2,
        "macd": "bearish",
        "trend": "uptrend",
        "bb": "middle",
        "score": 60,
        "rec": "BUY",
        "sl": 1764.54,
        "sl_pct": 7.95,
        "tp1": 2171.11,
        "tp2": 2374.39,
        "sup": 1640.0,
        "res": 2209.0,
        "atr": 101.64,
        "bid": 1913.17,
        "ask": 1920.83
      },
      {
        "sym": "SAMI",
        "price": 471.0,
        "chgPct": -0.84,
        "vol": 20657,
        "volRatio": 0.32,
        "rsi": 56.2,
        "rsiPrev": 56.5,
        "macd": "bullish",
        "trend": "downtrend",
        "bb": "middle",
        "score": 60,
        "rec": "BUY",
        "sl": 435.43,
        "sl_pct": 7.55,
        "tp1": 530.29,
        "tp2": 577.71,
        "sup": 440.0,
        "res": 540.0,
        "atr": 23.71,
        "bid": 470.06,
        "ask": 471.94
      },
      {
        "sym": "YPFD",
        "price": 82125.0,
        "chgPct": 0.98,
        "vol": 279453,
        "volRatio": 0.86,
        "rsi": 80.4,
        "rsiPrev": 80.7,
        "macd": "bullish",
        "trend": "uptrend",
        "bb": "middle",
        "score": 60,
        "rec": "BUY",
        "sl": 77300.89,
        "sl_pct": 5.87,
        "tp1": 90165.18,
        "tp2": 96597.32,
        "sup": 64100.0,
        "res": 87225.0,
        "atr": 3216.07,
        "bid": 81960.75,
        "ask": 82289.25
      },
      {
        "sym": "LOMA",
        "price": 3422.5,
        "chgPct": -2.84,
        "vol": 170144,
        "volRatio": 0.49,
        "rsi": 53.0,
        "rsiPrev": 62.6,
        "macd": "bearish",
        "trend": "uptrend",
        "bb": "middle",
        "score": 55,
        "rec": "HOLD",
        "sl": 3194.02,
        "sl_pct": 6.68,
        "tp1": 3803.3,
        "tp2": 4107.95,
        "sup": 3050.0,
        "res": 3772.5,
        "atr": 152.32,
        "bid": 3415.66,
        "ask": 3429.34
      },
      {
        "sym": "CELU",
        "price": 280.5,
        "chgPct": -2.77,
        "vol": 57777,
        "volRatio": 0.39,
        "rsi": 53.7,
        "rsiPrev": 57.5,
        "macd": "bearish",
        "trend": "uptrend",
        "bb": "middle",
        "score": 55,
        "rec": "HOLD",
        "sl": 245.52,
        "sl_pct": 12.47,
        "tp1": 338.8,
        "tp2": 385.45,
        "sup": 257.5,
        "res": 370.0,
        "atr": 23.32,
        "bid": 279.94,
        "ask": 281.06
      },
      {
        "sym": "VALO",
        "price": 626.5,
        "chgPct": 0.24,
        "vol": 1964576,
        "volRatio": 1.39,
        "rsi": 22.2,
        "rsiPrev": 20.5,
        "macd": "bearish",
        "trend": "downtrend",
        "bb": "middle",
        "score": 55,
        "rec": "HOLD",
        "sl": 596.77,
        "sl_pct": 4.75,
        "tp1": 676.05,
        "tp2": 715.7,
        "sup": 621.0,
        "res": 712.0,
        "atr": 19.82,
        "bid": 625.25,
        "ask": 627.75
      },
      {
        "sym": "FERR",
        "price": 20.35,
        "chgPct": -2.16,
        "vol": 591402,
        "volRatio": 1.7,
        "rsi": 46.2,
        "rsiPrev": 53.4,
        "macd": "bearish",
        "trend": "downtrend",
        "bb": "middle",
        "score": 45,
        "rec": "HOLD",
        "sl": 18.81,
        "sl_pct": 7.58,
        "tp1": 22.92,
        "tp2": 24.98,
        "sup": 19.7,
        "res": 22.85,
        "atr": 1.03,
        "bid": 20.31,
        "ask": 20.39
      },
      {
        "sym": "COME",
        "price": 43.95,
        "chgPct": 0.14,
        "vol": 7206152,
        "volRatio": 0.64,
        "rsi": 47.5,
        "rsiPrev": 49.4,
        "macd": "bearish",
        "trend": "downtrend",
        "bb": "middle",
        "score": 35,
        "rec": "SELL",
        "sl": 40.42,
        "sl_pct": 8.03,
        "tp1": 49.83,
        "tp2": 54.54,
        "sup": 42.0,
        "res": 51.8,
        "atr": 2.35,
        "bid": 43.86,
        "ask": 44.04
      },
      {
        "sym": "TRAN",
        "price": 3875.0,
        "chgPct": 0.32,
        "vol": 357997,
        "volRatio": 0.53,
        "rsi": 53.1,
        "rsiPrev": 49.5,
        "macd": "bearish",
        "trend": "downtrend",
        "bb": "middle",
        "score": 35,
        "rec": "SELL",
        "sl": 3664.73,
        "sl_pct": 5.43,
        "tp1": 4225.45,
        "tp2": 4505.8,
        "sup": 3570.0,
        "res": 4120.0,
        "atr": 140.18,
        "bid": 3867.25,
        "ask": 3882.75
      },
      {
        "sym": "AGRO",
        "price": 41.5,
        "chgPct": -1.43,
        "vol": 1516868,
        "volRatio": 0.73,
        "rsi": 53.1,
        "rsiPrev": 54.1,
        "macd": "bearish",
        "trend": "downtrend",
        "bb": "middle",
        "score": 35,
        "rec": "SELL",
        "sl": 38.04,
        "sl_pct": 8.34,
        "tp1": 47.27,
        "tp2": 51.88,
        "sup": 36.7,
        "res": 47.9,
        "atr": 2.31,
        "bid": 41.42,
        "ask": 41.58
      },
      {
        "sym": "MORI",
        "price": 27.9,
        "chgPct": -0.36,
        "vol": 1763111,
        "volRatio": 0.99,
        "rsi": 51.3,
        "rsiPrev": 56.6,
        "macd": "bearish",
        "trend": "downtrend",
        "bb": "middle",
        "score": 35,
        "rec": "SELL",
        "sl": 25.55,
        "sl_pct": 8.41,
        "tp1": 31.81,
        "tp2": 34.94,
        "sup": 25.4,
        "res": 32.3,
        "atr": 1.56,
        "bid": 27.84,
        "ask": 27.96
      },
      {
        "sym": "BHIP",
        "price": 329.0,
        "chgPct": -0.45,
        "vol": 252851,
        "volRatio": 0.57,
        "rsi": 49.5,
        "rsiPrev": 58.2,
        "macd": "bearish",
        "trend": "downtrend",
        "bb": "middle",
        "score": 35,
        "rec": "SELL",
        "sl": 300.29,
        "sl_pct": 8.73,
        "tp1": 376.86,
        "tp2": 415.14,
        "sup": 290.0,
        "res": 374.0,
        "atr": 19.14,
        "bid": 328.34,
        "ask": 329.66
      },
      {
        "sym": "INVJ",
        "price": 428.0,
        "chgPct": -3.17,
        "vol": 41122,
        "volRatio": 0.54,
        "rsi": 53.0,
        "rsiPrev": 59.4,
        "macd": "bearish",
        "trend": "downtrend",
        "bb": "middle",
        "score": 30,
        "rec": "SELL",
        "sl": 385.14,
        "sl_pct": 10.01,
        "tp1": 499.43,
        "tp2": 556.57,
        "sup": 410.0,
        "res": 518.0,
        "atr": 28.57,
        "bid": 427.14,
        "ask": 428.86
      }
    ],
    "count": 36,
    "sentiment": "bullish"
  },
  "cedear": {
    "data": [
      {
        "sym": "KO",
        "price": 25200.0,
        "chgPct": 2.4,
        "vol": 90798,
        "volRatio": 1.43,
        "rsi": 63.6,
        "rsiPrev": 53.5,
        "macd": "bullish",
        "trend": "uptrend",
        "bb": "upper",
        "score": 100,
        "rec": "STRONG_BUY",
        "sl": 24408.21,
        "sl_pct": 3.14,
        "tp1": 26519.64,
        "tp2": 27575.36,
        "sup": 23250.0,
        "res": 25380.0,
        "atr": 527.86,
        "bid": 25149.6,
        "ask": 25250.4
      },
      {
        "sym": "JPM",
        "price": 31220.0,
        "chgPct": -0.95,
        "vol": 5609,
        "volRatio": 0.34,
        "rsi": 65.6,
        "rsiPrev": 69.5,
        "macd": "bullish",
        "trend": "uptrend",
        "bb": "middle",
        "score": 85,
        "rec": "STRONG_BUY",
        "sl": 30279.29,
        "sl_pct": 3.01,
        "tp1": 32787.86,
        "tp2": 34042.14,
        "sup": 29160.0,
        "res": 32000.0,
        "atr": 627.14,
        "bid": 31157.56,
        "ask": 31282.44
      },
      {
        "sym": "JNJ",
        "price": 24040.0,
        "chgPct": 0.46,
        "vol": 11429,
        "volRatio": 0.79,
        "rsi": 68.6,
        "rsiPrev": 68.1,
        "macd": "bullish",
        "trend": "uptrend",
        "bb": "upper",
        "score": 85,
        "rec": "STRONG_BUY",
        "sl": 23338.22,
        "sl_pct": 2.92,
        "tp1": 25209.63,
        "tp2": 26145.33,
        "sup": 21850.0,
        "res": 24240.0,
        "atr": 467.85,
        "bid": 23991.92,
        "ask": 24088.08
      },
      {
        "sym": "BRKB",
        "price": 33240.0,
        "chgPct": -0.84,
        "vol": 32173,
        "volRatio": 0.88,
        "rsi": 63.2,
        "rsiPrev": 63.6,
        "macd": "bullish",
        "trend": "uptrend",
        "bb": "middle",
        "score": 85,
        "rec": "STRONG_BUY",
        "sl": 32453.57,
        "sl_pct": 2.37,
        "tp1": 34550.71,
        "tp2": 35599.29,
        "sup": 31620.0,
        "res": 33860.0,
        "atr": 524.29,
        "bid": 33173.52,
        "ask": 33306.48
      },
      {
        "sym": "QQQ",
        "price": 52450.0,
        "chgPct": -1.87,
        "vol": 116062,
        "volRatio": 2.03,
        "rsi": 47.5,
        "rsiPrev": 56.1,
        "macd": "bearish",
        "trend": "uptrend",
        "bb": "middle",
        "score": 80,
        "rec": "STRONG_BUY",
        "sl": 50620.54,
        "sl_pct": 3.49,
        "tp1": 55499.11,
        "tp2": 57938.39,
        "sup": 51700.0,
        "res": 56525.0,
        "atr": 1219.64,
        "bid": 52345.1,
        "ask": 52554.9
      },
      {
        "sym": "AMGN",
        "price": 16980.0,
        "chgPct": -2.41,
        "vol": 686,
        "volRatio": 0.3,
        "rsi": 56.5,
        "rsiPrev": 69.3,
        "macd": "bullish",
        "trend": "uptrend",
        "bb": "middle",
        "score": 80,
        "rec": "STRONG_BUY",
        "sl": 16440.0,
        "sl_pct": 3.18,
        "tp1": 17880.0,
        "tp2": 18600.0,
        "sup": 15920.0,
        "res": 18030.0,
        "atr": 360.0,
        "bid": 16946.04,
        "ask": 17013.96
      },
      {
        "sym": "AMZN",
        "price": 2487.0,
        "chgPct": -2.85,
        "vol": 584048,
        "volRatio": 0.91,
        "rsi": 23.5,
        "rsiPrev": 32.2,
        "macd": "bearish",
        "trend": "uptrend",
        "bb": "lower",
        "score": 75,
        "rec": "STRONG_BUY",
        "sl": 2369.36,
        "sl_pct": 4.73,
        "tp1": 2683.07,
        "tp2": 2839.93,
        "sup": 2482.0,
        "res": 2830.0,
        "atr": 78.43,
        "bid": 2482.03,
        "ask": 2491.97
      },
      {
        "sym": "MCD",
        "price": 17810.0,
        "chgPct": 0.0,
        "vol": 157747,
        "volRatio": 1.89,
        "rsi": 58.6,
        "rsiPrev": 62.4,
        "macd": "bullish",
        "trend": "downtrend",
        "bb": "middle",
        "score": 75,
        "rec": "STRONG_BUY",
        "sl": 17336.43,
        "sl_pct": 2.66,
        "tp1": 18599.28,
        "tp2": 19230.71,
        "sup": 16919.92,
        "res": 18080.0,
        "atr": 315.71,
        "bid": 17774.38,
        "ask": 17845.62
      },
      {
        "sym": "SPY",
        "price": 18260.0,
        "chgPct": -1.62,
        "vol": 492509,
        "volRatio": 1.65,
        "rsi": 47.6,
        "rsiPrev": 58.9,
        "macd": "bearish",
        "trend": "uptrend",
        "bb": "middle",
        "score": 75,
        "rec": "STRONG_BUY",
        "sl": 17152.5,
        "sl_pct": 6.07,
        "tp1": 20105.83,
        "tp2": 21582.5,
        "sup": 18133.33,
        "res": 23000.0,
        "atr": 738.33,
        "bid": 18223.48,
        "ask": 18296.52
      },
      {
        "sym": "AAPL",
        "price": 22060.0,
        "chgPct": 0.14,
        "vol": 67276,
        "volRatio": 1.08,
        "rsi": 43.4,
        "rsiPrev": 44.2,
        "macd": "bearish",
        "trend": "uptrend",
        "bb": "middle",
        "score": 70,
        "rec": "BUY",
        "sl": 21125.71,
        "sl_pct": 4.24,
        "tp1": 23617.14,
        "tp2": 24862.86,
        "sup": 21720.0,
        "res": 24200.0,
        "atr": 622.86,
        "bid": 22015.88,
        "ask": 22104.12
      },
      {
        "sym": "NVDA",
        "price": 12660.0,
        "chgPct": -3.28,
        "vol": 857437,
        "volRatio": 1.58,
        "rsi": 36.7,
        "rsiPrev": 38.3,
        "macd": "bearish",
        "trend": "uptrend",
        "bb": "middle",
        "score": 70,
        "rec": "BUY",
        "sl": 11928.21,
        "sl_pct": 5.78,
        "tp1": 13879.64,
        "tp2": 14855.36,
        "sup": 12580.0,
        "res": 14659.99,
        "atr": 487.86,
        "bid": 12634.68,
        "ask": 12685.32
      },
      {
        "sym": "QCOM",
        "price": 26360.0,
        "chgPct": -5.65,
        "vol": 142800,
        "volRatio": 1.75,
        "rsi": 45.3,
        "rsiPrev": 51.3,
        "macd": "bearish",
        "trend": "uptrend",
        "bb": "middle",
        "score": 70,
        "rec": "BUY",
        "sl": 22421.44,
        "sl_pct": 14.94,
        "tp1": 32924.26,
        "tp2": 38175.67,
        "sup": 25819.94,
        "res": 35139.91,
        "atr": 2625.7,
        "bid": 26307.28,
        "ask": 26412.72
      },
      {
        "sym": "TSM",
        "price": 68750.0,
        "chgPct": -4.28,
        "vol": 27808,
        "volRatio": 1.71,
        "rsi": 55.0,
        "rsiPrev": 65.2,
        "macd": "bearish",
        "trend": "uptrend",
        "bb": "middle",
        "score": 70,
        "rec": "BUY",
        "sl": 64491.07,
        "sl_pct": 6.19,
        "tp1": 75848.21,
        "tp2": 81526.79,
        "sup": 63625.0,
        "res": 75300.0,
        "atr": 2839.29,
        "bid": 68612.5,
        "ask": 68887.5
      },
      {
        "sym": "GS",
        "price": 116600.0,
        "chgPct": -3.02,
        "vol": 1768,
        "volRatio": 1.59,
        "rsi": 56.7,
        "rsiPrev": 63.8,
        "macd": "bearish",
        "trend": "uptrend",
        "bb": "middle",
        "score": 70,
        "rec": "BUY",
        "sl": 111186.61,
        "sl_pct": 4.64,
        "tp1": 125622.32,
        "tp2": 132840.17,
        "sup": 105824.68,
        "res": 127800.0,
        "atr": 3608.93,
        "bid": 116366.8,
        "ask": 116833.2
      },
      {
        "sym": "TSLA",
        "price": 38500.0,
        "chgPct": -3.56,
        "vol": 56451,
        "volRatio": 0.85,
        "rsi": 40.3,
        "rsiPrev": 45.1,
        "macd": "bearish",
        "trend": "uptrend",
        "bb": "lower",
        "score": 65,
        "rec": "BUY",
        "sl": 36029.29,
        "sl_pct": 6.42,
        "tp1": 42617.86,
        "tp2": 45912.14,
        "sup": 38240.0,
        "res": 44660.0,
        "atr": 1647.14,
        "bid": 38423.0,
        "ask": 38577.0
      },
      {
        "sym": "SONY",
        "price": 3910.0,
        "chgPct": -2.74,
        "vol": 4366,
        "volRatio": 0.32,
        "rsi": 37.9,
        "rsiPrev": 39.2,
        "macd": "bearish",
        "trend": "uptrend",
        "bb": "lower",
        "score": 65,
        "rec": "BUY",
        "sl": 3761.88,
        "sl_pct": 3.79,
        "tp1": 4156.88,
        "tp2": 4354.38,
        "sup": 3902.5,
        "res": 4340.0,
        "atr": 98.75,
        "bid": 3902.18,
        "ask": 3917.82
      },
      {
        "sym": "MSFT",
        "price": 20060.0,
        "chgPct": -1.47,
        "vol": 158821,
        "volRatio": 0.49,
        "rsi": 45.1,
        "rsiPrev": 45.4,
        "macd": "bearish",
        "trend": "uptrend",
        "bb": "middle",
        "score": 60,
        "rec": "BUY",
        "sl": 19059.29,
        "sl_pct": 4.99,
        "tp1": 21727.86,
        "tp2": 23062.14,
        "sup": 19849.97,
        "res": 23100.0,
        "atr": 667.14,
        "bid": 20019.88,
        "ask": 20100.12
      },
      {
        "sym": "INTC",
        "price": 32420.0,
        "chgPct": 0.12,
        "vol": 140587,
        "volRatio": 0.92,
        "rsi": 42.2,
        "rsiPrev": 41.3,
        "macd": "bearish",
        "trend": "uptrend",
        "bb": "middle",
        "score": 60,
        "rec": "BUY",
        "sl": 28612.14,
        "sl_pct": 11.75,
        "tp1": 38766.43,
        "tp2": 43843.57,
        "sup": 29700.0,
        "res": 37400.0,
        "atr": 2538.57,
        "bid": 32355.16,
        "ask": 32484.84
      },
      {
        "sym": "PEP",
        "price": 12120.0,
        "chgPct": 0.92,
        "vol": 22114,
        "volRatio": 0.85,
        "rsi": 47.8,
        "rsiPrev": 40.9,
        "macd": "bullish",
        "trend": "downtrend",
        "bb": "middle",
        "score": 60,
        "rec": "BUY",
        "sl": 11741.79,
        "sl_pct": 3.12,
        "tp1": 12750.35,
        "tp2": 13254.64,
        "sup": 11679.92,
        "res": 12629.91,
        "atr": 252.14,
        "bid": 12095.76,
        "ask": 12144.24
      },
      {
        "sym": "WMT",
        "price": 10100.0,
        "chgPct": 1.15,
        "vol": 66924,
        "volRatio": 0.89,
        "rsi": 52.8,
        "rsiPrev": 31.9,
        "macd": "bullish",
        "trend": "downtrend",
        "bb": "middle",
        "score": 60,
        "rec": "BUY",
        "sl": 9753.39,
        "sl_pct": 3.43,
        "tp1": 10677.68,
        "tp2": 11139.82,
        "sup": 9380.0,
        "res": 11200.0,
        "atr": 231.07,
        "bid": 10079.8,
        "ask": 10120.2
      },
      {
        "sym": "V",
        "price": 27100.0,
        "chgPct": -0.81,
        "vol": 22403,
        "volRatio": 0.88,
        "rsi": 47.7,
        "rsiPrev": 49.7,
        "macd": "bearish",
        "trend": "uptrend",
        "bb": "middle",
        "score": 60,
        "rec": "BUY",
        "sl": 26315.71,
        "sl_pct": 2.89,
        "tp1": 28407.14,
        "tp2": 29452.86,
        "sup": 25880.0,
        "res": 27680.0,
        "atr": 522.86,
        "bid": 27045.8,
        "ask": 27154.2
      },
      {
        "sym": "XOM",
        "price": 22800.0,
        "chgPct": 1.2,
        "vol": 6462,
        "volRatio": 0.58,
        "rsi": 48.4,
        "rsiPrev": 42.2,
        "macd": "bullish",
        "trend": "downtrend",
        "bb": "middle",
        "score": 60,
        "rec": "BUY",
        "sl": 21990.0,
        "sl_pct": 3.55,
        "tp1": 24150.0,
        "tp2": 25230.0,
        "sup": 21490.0,
        "res": 24330.0,
        "atr": 540.0,
        "bid": 22754.4,
        "ask": 22845.6
      },
      {
        "sym": "CVX",
        "price": 17930.0,
        "chgPct": 1.64,
        "vol": 17646,
        "volRatio": 0.86,
        "rsi": 54.0,
        "rsiPrev": 47.8,
        "macd": "bullish",
        "trend": "downtrend",
        "bb": "middle",
        "score": 60,
        "rec": "BUY",
        "sl": 17321.43,
        "sl_pct": 3.39,
        "tp1": 18944.29,
        "tp2": 19755.71,
        "sup": 16720.0,
        "res": 18520.0,
        "atr": 405.71,
        "bid": 17894.14,
        "ask": 17965.86
      },
      {
        "sym": "PFE",
        "price": 9680.0,
        "chgPct": 0.0,
        "vol": 16961,
        "volRatio": 0.89,
        "rsi": 56.6,
        "rsiPrev": 56.6,
        "macd": "bullish",
        "trend": "downtrend",
        "bb": "middle",
        "score": 60,
        "rec": "BUY",
        "sl": 9427.14,
        "sl_pct": 2.61,
        "tp1": 10101.43,
        "tp2": 10438.57,
        "sup": 9340.0,
        "res": 9955.0,
        "atr": 168.57,
        "bid": 9660.64,
        "ask": 9699.36
      },
      {
        "sym": "GLD",
        "price": 11300.0,
        "chgPct": -4.32,
        "vol": 399699,
        "volRatio": 2.74,
        "rsi": 24.2,
        "rsiPrev": 37.1,
        "macd": "bearish",
        "trend": "downtrend",
        "bb": "lower",
        "score": 60,
        "rec": "BUY",
        "sl": 10910.0,
        "sl_pct": 3.45,
        "tp1": 11950.0,
        "tp2": 12470.0,
        "sup": 11270.0,
        "res": 12850.0,
        "atr": 260.0,
        "bid": 11277.4,
        "ask": 11322.6
      },
      {
        "sym": "LLY",
        "price": 30700.0,
        "chgPct": -0.45,
        "vol": 12526,
        "volRatio": 0.71,
        "rsi": 73.2,
        "rsiPrev": 76.9,
        "macd": "bullish",
        "trend": "uptrend",
        "bb": "middle",
        "score": 60,
        "rec": "BUY",
        "sl": 29187.14,
        "sl_pct": 4.93,
        "tp1": 33221.43,
        "tp2": 35238.57,
        "sup": 25980.0,
        "res": 31960.0,
        "atr": 1008.57,
        "bid": 30638.6,
        "ask": 30761.4
      },
      {
        "sym": "GOOGL",
        "price": 9280.0,
        "chgPct": -2.52,
        "vol": 189773,
        "volRatio": 0.69,
        "rsi": 32.1,
        "rsiPrev": 35.7,
        "macd": "bearish",
        "trend": "uptrend",
        "bb": "middle",
        "score": 55,
        "rec": "HOLD",
        "sl": 8908.21,
        "sl_pct": 4.01,
        "tp1": 9899.64,
        "tp2": 10395.36,
        "sup": 9240.0,
        "res": 10480.0,
        "atr": 247.86,
        "bid": 9261.44,
        "ask": 9298.56
      },
      {
        "sym": "NFLX",
        "price": 2575.0,
        "chgPct": 0.29,
        "vol": 163082,
        "volRatio": 1.1,
        "rsi": 20.0,
        "rsiPrev": 22.6,
        "macd": "bearish",
        "trend": "downtrend",
        "bb": "middle",
        "score": 55,
        "rec": "HOLD",
        "sl": 2480.18,
        "sl_pct": 3.68,
        "tp1": 2733.04,
        "tp2": 2859.46,
        "sup": 2547.5,
        "res": 2835.0,
        "atr": 63.21,
        "bid": 2569.85,
        "ask": 2580.15
      },
      {
        "sym": "AMD",
        "price": 68350.0,
        "chgPct": -3.73,
        "vol": 44849,
        "volRatio": 0.92,
        "rsi": 52.6,
        "rsiPrev": 56.3,
        "macd": "bearish",
        "trend": "uptrend",
        "bb": "middle",
        "score": 55,
        "rec": "HOLD",
        "sl": 60571.43,
        "sl_pct": 11.38,
        "tp1": 81314.29,
        "tp2": 91685.71,
        "sup": 58500.0,
        "res": 82625.0,
        "atr": 5185.71,
        "bid": 68213.3,
        "ask": 68486.7
      },
      {
        "sym": "CRM",
        "price": 14350.0,
        "chgPct": -2.45,
        "vol": 20625,
        "volRatio": 0.39,
        "rsi": 49.0,
        "rsiPrev": 49.0,
        "macd": "bearish",
        "trend": "uptrend",
        "bb": "middle",
        "score": 55,
        "rec": "HOLD",
        "sl": 13208.93,
        "sl_pct": 7.95,
        "tp1": 16251.79,
        "tp2": 17773.21,
        "sup": 13570.0,
        "res": 17540.0,
        "atr": 760.71,
        "bid": 14321.3,
        "ask": 14378.7
      },
      {
        "sym": "PYPL",
        "price": 7700.0,
        "chgPct": -1.53,
        "vol": 67299,
        "volRatio": 2.97,
        "rsi": 32.0,
        "rsiPrev": 34.5,
        "macd": "bearish",
        "trend": "downtrend",
        "bb": "lower",
        "score": 55,
        "rec": "HOLD",
        "sl": 7390.36,
        "sl_pct": 4.02,
        "tp1": 8216.07,
        "tp2": 8628.93,
        "sup": 7640.0,
        "res": 8554.98,
        "atr": 206.43,
        "bid": 7684.6,
        "ask": 7715.4
      },
      {
        "sym": "ARKK",
        "price": 11090.0,
        "chgPct": -2.38,
        "vol": 5407,
        "volRatio": 0.81,
        "rsi": 47.2,
        "rsiPrev": 56.3,
        "macd": "bearish",
        "trend": "uptrend",
        "bb": "middle",
        "score": 55,
        "rec": "HOLD",
        "sl": 10471.79,
        "sl_pct": 5.57,
        "tp1": 12120.36,
        "tp2": 12944.64,
        "sup": 10830.0,
        "res": 12280.0,
        "atr": 412.14,
        "bid": 11067.82,
        "ask": 11112.18
      },
      {
        "sym": "SLV",
        "price": 14540.0,
        "chgPct": -2.09,
        "vol": 129500,
        "volRatio": 1.39,
        "rsi": 23.2,
        "rsiPrev": 31.2,
        "macd": "bearish",
        "trend": "downtrend",
        "bb": "lower",
        "score": 50,
        "rec": "HOLD",
        "sl": 13707.5,
        "sl_pct": 5.73,
        "tp1": 15927.5,
        "tp2": 17037.5,
        "sup": 14470.0,
        "res": 19990.0,
        "atr": 555.0,
        "bid": 14510.92,
        "ask": 14569.08
      },
      {
        "sym": "GLOB",
        "price": 3077.5,
        "chgPct": -1.36,
        "vol": 101198,
        "volRatio": 0.24,
        "rsi": 40.7,
        "rsiPrev": 39.3,
        "macd": "bearish",
        "trend": "downtrend",
        "bb": "middle",
        "score": 35,
        "rec": "SELL",
        "sl": 2806.43,
        "sl_pct": 8.81,
        "tp1": 3529.29,
        "tp2": 3890.71,
        "sup": 2705.0,
        "res": 3700.0,
        "atr": 180.71,
        "bid": 3071.34,
        "ask": 3083.66
      },
      {
        "sym": "VALE",
        "price": 11260.0,
        "chgPct": -1.23,
        "vol": 89527,
        "volRatio": 0.54,
        "rsi": 31.6,
        "rsiPrev": 34.3,
        "macd": "bearish",
        "trend": "downtrend",
        "bb": "lower",
        "score": 35,
        "rec": "SELL",
        "sl": 10775.71,
        "sl_pct": 4.3,
        "tp1": 12067.14,
        "tp2": 12712.86,
        "sup": 11200.0,
        "res": 12700.0,
        "atr": 322.86,
        "bid": 11237.48,
        "ask": 11282.52
      },
      {
        "sym": "MELI",
        "price": 19960.0,
        "chgPct": -3.53,
        "vol": 414298,
        "volRatio": 0.88,
        "rsi": 41.5,
        "rsiPrev": 53.6,
        "macd": "bearish",
        "trend": "downtrend",
        "bb": "middle",
        "score": 30,
        "rec": "SELL",
        "sl": 19082.5,
        "sl_pct": 4.4,
        "tp1": 21422.5,
        "tp2": 22592.5,
        "sup": 19000.0,
        "res": 21560.0,
        "atr": 585.0,
        "bid": 19920.08,
        "ask": 19999.92
      },
      {
        "sym": "UBER",
        "price": 52100.0,
        "chgPct": -2.07,
        "vol": 9117,
        "volRatio": 0.68,
        "rsi": 35.4,
        "rsiPrev": 40.3,
        "macd": "bearish",
        "trend": "downtrend",
        "bb": "middle",
        "score": 30,
        "rec": "SELL",
        "sl": 49769.64,
        "sl_pct": 4.47,
        "tp1": 55983.93,
        "tp2": 59091.07,
        "sup": 51625.0,
        "res": 56500.0,
        "atr": 1553.57,
        "bid": 51995.8,
        "ask": 52204.2
      }
    ],
    "count": 37,
    "sentiment": "bullish"
  }
}